wagtail_tag_manager/__init__.py
wagtail_tag_manager/apps.py
wagtail_tag_manager/config.py
wagtail_tag_manager/consent.py
wagtail_tag_manager/context_processors.py
wagtail_tag_manager/decorators.py
wagtail_tag_manager/endpoints.py
wagtail_tag_manager/forms.py
wagtail_tag_manager/managers.py
wagtail_tag_manager/middleware.py
wagtail_tag_manager/mixins.py
wagtail_tag_manager/options.py
wagtail_tag_manager/settings.py
wagtail_tag_manager/strategy.py
wagtail_tag_manager/urls.py
wagtail_tag_manager/utils.py
wagtail_tag_manager/views.py
wagtail_tag_manager/wagtail_hooks.py
wagtail_tag_manager/webdriver.py
wagtail_tag_manager/widgets.py
wagtail_tag_manager/migrations/0001_initial.py
wagtail_tag_manager/migrations/0002_auto_20181111_1854.py
wagtail_tag_manager/migrations/0003_auto_20181206_1108.py
wagtail_tag_manager/migrations/0004_auto_20181206_1530.py
wagtail_tag_manager/migrations/0005_auto_20181227_1123.py
wagtail_tag_manager/migrations/0006_cookiebarsettings.py
wagtail_tag_manager/migrations/0007_auto_20190130_1435.py
wagtail_tag_manager/migrations/0008_auto_load_rename.py
wagtail_tag_manager/migrations/0009_auto_20190401_1550.py
wagtail_tag_manager/migrations/0010_auto_20190403_0639.py
wagtail_tag_manager/migrations/0011_auto_20190501_1049.py
wagtail_tag_manager/migrations/0012_auto_20190501_1118.py
wagtail_tag_manager/migrations/0013_auto_20190506_0705.py
wagtail_tag_manager/migrations/0014_auto_20190911_1116.py
wagtail_tag_manager/migrations/0015_cookieconsent.py
wagtail_tag_manager/migrations/0016_auto_20200210_1121.py
wagtail_tag_manager/migrations/0017_auto_20201028_0905.py
wagtail_tag_manager/migrations/0018_alter_constant_id_alter_cookiebarsettings_id_and_more.py
wagtail_tag_manager/migrations/0019_cookieconsentsettings.py
wagtail_tag_manager/migrations/__init__.py
wagtail_tag_manager/models/__init__.py
wagtail_tag_manager/models/constants.py
wagtail_tag_manager/models/others.py
wagtail_tag_manager/models/tags.py
wagtail_tag_manager/models/triggers.py
wagtail_tag_manager-2.0.0.dist-info/LICENSE
wagtail_tag_manager-2.0.0.dist-info/METADATA
wagtail_tag_manager-2.0.0.dist-info/WHEEL
wagtail_tag_manager-2.0.0.dist-info/top_level.txt
wagtail_tag_manager-2.0.0.dist-info/RECORD
