Metadata-Version: 2.1
Name: wagtail-tag-manager
Version: 2.0.0
Summary: A Wagtail add-on for managing tags.
Home-page: https://github.com/jberghoef/wagtail-tag-manager
Author: Jasper Berghoef
Author-email: j.berghoef@me.com
License: BSD 3-Clause
Classifier: Development Status :: 4 - Beta
Classifier: Environment :: Web Environment
Classifier: Intended Audience :: Developers
Classifier: License :: OSI Approved :: BSD License
Classifier: Operating System :: OS Independent
Classifier: Programming Language :: Python :: 3.6
Classifier: Programming Language :: Python :: 3.7
Classifier: Programming Language :: Python :: 3.8
Classifier: Programming Language :: Python :: 3.9
Classifier: Programming Language :: Python :: 3.10
Classifier: Framework :: Django :: 2.2
Classifier: Framework :: Django :: 3.0
Classifier: Framework :: Django :: 3.1
Classifier: Framework :: Django :: 3.2
Classifier: Framework :: Django :: 4.0
Classifier: Framework :: Wagtail :: 2
Classifier: Framework :: Wagtail :: 3
Classifier: Framework :: Wagtail :: 4
Provides-Extra: docs
Provides-Extra: test
License-File: LICENSE
